ai_sdk/__init__.py
ai_sdk/embed.py
ai_sdk/generate_object.py
ai_sdk/generate_text.py
ai_sdk/py.typed
ai_sdk/tool.py
ai_sdk/types.py
ai_sdk/providers/anthropic.py
ai_sdk/providers/embedding_model.py
ai_sdk/providers/language_model.py
ai_sdk/providers/openai.py
ai_sdk_python-0.1.0.dist-info/METADATA
ai_sdk_python-0.1.0.dist-info/WHEEL
ai_sdk_python-0.1.0.dist-info/RECORD
