Metadata-Version: 2.4
Name: ai-sdk-python
Version: 0.1.0
Summary: The easiest, safest, and cleanest way to use AI in your Python code. Inspired by the Vercel AI SDK.
Author-email: Asanshay Gupta <asanshay@bharatgupta.com>
Requires-Python: >=3.12
Requires-Dist: openai>=1.93.2
Requires-Dist: pydantic>=2.7.1
Requires-Dist: python-dotenv>=1.1.1
Provides-Extra: dev
Requires-Dist: pytest-asyncio>=0.23.6; extra == 'dev'
Requires-Dist: pytest>=8.2.0; extra == 'dev'
